inference_api/__init__.py
inference_api/cli.py
inference_api/main.py
inference_api-0.0.1.dist-info/METADATA
inference_api-0.0.1.dist-info/WHEEL
inference_api-0.0.1.dist-info/entry_points.txt
inference_api-0.0.1.dist-info/RECORD
